molecular_builder/__init__.py
molecular_builder/core.py
molecular_builder/crystals.py
molecular_builder/geometry.py
molecular_builder/utils.py
molecular_builder/data_files/water.pdb
molecular_builder/data_files/water.xyz
molecular_builder-0.3.0.dist-info/LICENSE
molecular_builder-0.3.0.dist-info/METADATA
molecular_builder-0.3.0.dist-info/WHEEL
molecular_builder-0.3.0.dist-info/top_level.txt
molecular_builder-0.3.0.dist-info/RECORD
