Metadata-Version: 2.1
Name: molecular-builder
Version: 0.3.0
Summary: Package for building molecular systems
Home-page: https://github.com/henriasv/molecular-builder
Author: Henrik Andersen Sveinsson
Author-email: henriasv@fys.uio.no
License: UNKNOWN
Platform: UNKNOWN
Classifier: Programming Language :: Python :: 3
Classifier: Operating System :: OS Independent
Requires-Python: >=3.7
Requires-Dist: ase
Requires-Dist: requests
Requires-Dist: requests-cache
Requires-Dist: clint
Requires-Dist: werkzeug
Requires-Dist: cython
Requires-Dist: recommonmark
Requires-Dist: ovito
Requires-Dist: noise
